np_mlp/__init__.py
np_mlp/activations.py
np_mlp/data_processing.py
np_mlp/helpers.py
np_mlp/initializers.py
np_mlp/layers.py
np_mlp/losses.py
np_mlp/model_utils.py
np_mlp/models.py
np_mlp/optimizers.py
np_mlp/tensor.py
np_mlp/train.py
np_mlp-0.1.0.2.dist-info/LICENSE
np_mlp-0.1.0.2.dist-info/METADATA
np_mlp-0.1.0.2.dist-info/WHEEL
np_mlp-0.1.0.2.dist-info/top_level.txt
np_mlp-0.1.0.2.dist-info/RECORD
