Metadata-Version: 2.1
Name: np-mlp
Version: 0.1.0.2
Summary: Light-weight implementation of a MLP library using only Numpy
Home-page: https://github.com/gonzalofrancoceballos/MLP
Author: Gonzalo Franco
Author-email: gonzalofrancoceballos@gmail.com
License: UNKNOWN
Keywords: data science,neural networks,mlp
Platform: UNKNOWN
Classifier: Development Status :: 4 - Beta
Classifier: Intended Audience :: Developers
Classifier: Intended Audience :: Science/Research
Classifier: Topic :: Scientific/Engineering :: Artificial Intelligence
Classifier: License :: OSI Approved :: GNU General Public License (GPL)
Classifier: Programming Language :: Python :: 3
Classifier: Programming Language :: Python :: 3.5
Classifier: Programming Language :: Python :: 3.6
Classifier: Programming Language :: Python :: 3.7
Classifier: Programming Language :: Python :: 3.8
Requires-Python: >=3.5, <3.9
Requires-Dist: numpy
Requires-Dist: pandas
